cekit/__init__.py
cekit/builder.py
cekit/cekit_types.py
cekit/cli.py
cekit/config.py
cekit/crypto.py
cekit/errors.py
cekit/log.py
cekit/template_helper.py
cekit/tools.py
cekit/version.py
cekit/builders/__init__.py
cekit/builders/buildah.py
cekit/builders/docker_builder.py
cekit/builders/oci_builder.py
cekit/builders/osbs.py
cekit/builders/podman.py
cekit/cache/__init__.py
cekit/cache/artifact.py
cekit/cache/cli.py
cekit/descriptor/__init__.py
cekit/descriptor/arg.py
cekit/descriptor/base.py
cekit/descriptor/env.py
cekit/descriptor/execute.py
cekit/descriptor/image.py
cekit/descriptor/label.py
cekit/descriptor/module.py
cekit/descriptor/modules.py
cekit/descriptor/osbs.py
cekit/descriptor/overrides.py
cekit/descriptor/packages.py
cekit/descriptor/port.py
cekit/descriptor/resource.py
cekit/descriptor/run.py
cekit/descriptor/volume.py
cekit/generator/__init__.py
cekit/generator/base.py
cekit/generator/behave.py
cekit/generator/docker.py
cekit/generator/legacy_version.py
cekit/generator/osbs.py
cekit/templates/__init__.py
cekit/templates/help.jinja
cekit/templates/template.jinja
cekit/test/__init__.py
cekit/test/behave_runner.py
cekit/test/behave_tester.py
cekit/test/collector.py
cekit-4.16.0.dist-info/licenses/LICENSE
cekit-4.16.0.dist-info/METADATA
cekit-4.16.0.dist-info/WHEEL
cekit-4.16.0.dist-info/entry_points.txt
cekit-4.16.0.dist-info/top_level.txt
cekit-4.16.0.dist-info/RECORD
