Metadata-Version: 2.4
Name: cekit
Version: 4.16.0
Summary: Container image creation tool
Home-page: https://github.com/cekit/cekit
Download-URL: https://github.com/cekit/cekit/archive/4.16.0.tar.gz
Author: CEKit team
Author-email: cekit@cekit.io
License: MIT
License-File: LICENSE
Requires-Dist: Jinja2>=2.7
Requires-Dist: PyYAML>=3.10
Requires-Dist: click>=6.7
Requires-Dist: colorlog>=2.10.0
Requires-Dist: packaging>=19.0
Requires-Dist: pykwalify>=1.6.0
Requires-Dist: ruamel.yaml<=0.18.3; python_version < "3.7"
Dynamic: author
Dynamic: author-email
Dynamic: description
Dynamic: download-url
Dynamic: home-page
Dynamic: license
Dynamic: license-file
Dynamic: requires-dist
Dynamic: summary
